Metadata-Version: 2.1
Name: pydocker
Version: 1.0.6
Summary: Easy generator Dockerfile for humans.
Home-page: https://github.com/jen-soft/pydocker
Author: Jen-Soft
Author-email: jen.soft.master@gmail.com
Maintainer: Jen-Soft
Maintainer-email: jen.soft.master@gmail.com
License: Apache License 2.0 and MIT License
Download-URL: https://github.com/jen-soft/pydocker/archive/v1.0.6.zip
Keywords: dockerfile,docker,pydocker,python,deploy,docker-image,for-humans
Platform: any
Classifier: Development Status :: 5 - Production/Stable
Classifier: Environment :: Console
Classifier: Intended Audience :: Developers
Classifier: License :: OSI Approved :: Apache Software License
Classifier: License :: OSI Approved :: Apple Public Source License
Classifier: License :: OSI Approved :: MIT License
Classifier: Natural Language :: English
Classifier: Natural Language :: Russian
Classifier: Programming Language :: Python :: 3.7
Classifier: Programming Language :: Python :: 3.6
Classifier: Programming Language :: Python :: 3.5
Classifier: Programming Language :: Python :: 3.4
Classifier: Programming Language :: Python :: 3
Classifier: Programming Language :: Python :: 2.7
Classifier: Programming Language :: Python :: 2
Classifier: Programming Language :: Python :: Implementation
Classifier: Topic :: Software Development
Classifier: Topic :: System
Classifier: Topic :: System :: Clustering
Classifier: Topic :: System :: Emulators
Classifier: Topic :: Internet
Classifier: Topic :: Internet :: WWW/HTTP :: HTTP Servers
License-File: LICENSE.Apache-2.0
License-File: LICENSE.MIT
